[
    {
        "ID": 9001, 
        "Name": "E00", 
        "Health": 700, 
        "Mana": 100, 
        "Energy": 100, 
        "Strength": 25, 
        "Intellect": 55, 
        "Agile": 35, 
        "AttDamage": 200, 
        "MagDamage": 200, 
        "AttDefense": 10, 
        "MagDefense": 50, 
        "Hit": 50, 
        "Dodge": 0, 
        "Critical": 10, 
        "CriticalDamage": 20, 
        "AttackSpeed": 10, 
        "MoveSpeed": 15, 
        "Rank": 1, 
        "IsLocked": 0, 
        "IsBattle": 1
    }, 
    {
        "ID": 9002, 
        "Name": "E01", 
        "Health": 820, 
        "Mana": 101, 
        "Energy": 0, 
        "Strength": 34, 
        "Intellect": 40, 
        "Agile": 60, 
        "AttDamage": 150, 
        "MagDamage": 0, 
        "AttDefense": 20, 
        "MagDefense": 10, 
        "Hit": 50, 
        "Dodge": 0, 
        "Critical": 11, 
        "CriticalDamage": 20, 
        "AttackSpeed": 11, 
        "MoveSpeed": 16, 
        "Rank": 1, 
        "IsLocked": 1, 
        "IsBattle": 0
    }, 
    {
        "ID": 9003, 
        "Name": "E02", 
        "Health": 940, 
        "Mana": 102, 
        "Energy": 0, 
        "Strength": 57, 
        "Intellect": 20, 
        "Agile": 40, 
        "AttDamage": 90, 
        "MagDamage": 0, 
        "AttDefense": 30, 
        "MagDefense": 0, 
        "Hit": 50, 
        "Dodge": 0, 
        "Critical": 12, 
        "CriticalDamage": 20, 
        "AttackSpeed": 12, 
        "MoveSpeed": 17, 
        "Rank": 1, 
        "IsLocked": 1, 
        "IsBattle": 0
    }, 
    {
        "ID": 9004, 
        "Name": "E03", 
        "Health": 960, 
        "Mana": 103, 
        "Energy": 0, 
        "Strength": 58, 
        "Intellect": 21, 
        "Agile": 41, 
        "AttDamage": 301, 
        "MagDamage": 0, 
        "AttDefense": 31, 
        "MagDefense": 0, 
        "Hit": 50, 
        "Dodge": 0, 
        "Critical": 13, 
        "CriticalDamage": 21, 
        "AttackSpeed": 13, 
        "MoveSpeed": 18, 
        "Rank": 1, 
        "IsLocked": 1, 
        "IsBattle": 0
    }, 
    {
        "ID": 9005, 
        "Name": "E04", 
        "Health": 1080, 
        "Mana": 104, 
        "Energy": 0, 
        "Strength": 59, 
        "Intellect": 22, 
        "Agile": 42, 
        "AttDamage": 402, 
        "MagDamage": 0, 
        "AttDefense": 32, 
        "MagDefense": 1, 
        "Hit": 50, 
        "Dodge": 0, 
        "Critical": 14, 
        "CriticalDamage": 22, 
        "AttackSpeed": 14, 
        "MoveSpeed": 19, 
        "Rank": 1, 
        "IsLocked": 1, 
        "IsBattle": 0
    }, 
    {
        "ID": 9006, 
        "Name": "E05", 
        "Health": 1500, 
        "Mana": 105, 
        "Energy": 0, 
        "Strength": 60, 
        "Intellect": 23, 
        "Agile": 43, 
        "AttDamage": 525, 
        "MagDamage": 0, 
        "AttDefense": 33, 
        "MagDefense": 2, 
        "Hit": 50, 
        "Dodge": 0, 
        "Critical": 15, 
        "CriticalDamage": 23, 
        "AttackSpeed": 15, 
        "MoveSpeed": 20, 
        "Rank": 1, 
        "IsLocked": 1, 
        "IsBattle": 0
    }, 
    {
        "ID": 9007, 
        "Name": "E06", 
        "Health": 1601, 
        "Mana": 106, 
        "Energy": 0, 
        "Strength": 61, 
        "Intellect": 24, 
        "Agile": 44, 
        "AttDamage": 535, 
        "MagDamage": 0, 
        "AttDefense": 34, 
        "MagDefense": 3, 
        "Hit": 50, 
        "Dodge": 0, 
        "Critical": 16, 
        "CriticalDamage": 24, 
        "AttackSpeed": 16, 
        "MoveSpeed": 21, 
        "Rank": 1, 
        "IsLocked": 1, 
        "IsBattle": 0
    }, 
    {
        "ID": 9008, 
        "Name": "E07", 
        "Health": 1702, 
        "Mana": 107, 
        "Energy": 0, 
        "Strength": 62, 
        "Intellect": 25, 
        "Agile": 45, 
        "AttDamage": 570, 
        "MagDamage": 0, 
        "AttDefense": 35, 
        "MagDefense": 4, 
        "Hit": 50, 
        "Dodge": 0, 
        "Critical": 17, 
        "CriticalDamage": 25, 
        "AttackSpeed": 17, 
        "MoveSpeed": 22, 
        "Rank": 1, 
        "IsLocked": 1, 
        "IsBattle": 0
    }, 
    {
        "ID": 9009, 
        "Name": "E08", 
        "Health": 1803, 
        "Mana": 108, 
        "Energy": 0, 
        "Strength": 63, 
        "Intellect": 26, 
        "Agile": 46, 
        "AttDamage": 556, 
        "MagDamage": 0, 
        "AttDefense": 36, 
        "MagDefense": 5, 
        "Hit": 50, 
        "Dodge": 0, 
        "Critical": 18, 
        "CriticalDamage": 26, 
        "AttackSpeed": 18, 
        "MoveSpeed": 23, 
        "Rank": 1, 
        "IsLocked": 1, 
        "IsBattle": 0
    }, 
    {
        "ID": 9010, 
        "Name": "E09", 
        "Health": 1980, 
        "Mana": 109, 
        "Energy": 0, 
        "Strength": 64, 
        "Intellect": 27, 
        "Agile": 47, 
        "AttDamage": 575, 
        "MagDamage": 0, 
        "AttDefense": 37, 
        "MagDefense": 6, 
        "Hit": 50, 
        "Dodge": 0, 
        "Critical": 19, 
        "CriticalDamage": 27, 
        "AttackSpeed": 19, 
        "MoveSpeed": 24, 
        "Rank": 1, 
        "IsLocked": 1, 
        "IsBattle": 0
    }
]